[
  {
    "id": 1,
    "name": "Arafat Hossain",
    "picture": "https://randomuser.me/api/portraits/men/32.jpg",
    "email": "arafat.hossain@gmail.com",
    "days_since_contact": " 18 day ago",
    "status": "overdue",
    "tags": ["university", "close friend"],
    "bio": "We studied Computer Science together. Often discussed startups and built small projects.",
    "goal": 14,
    "next_due_date": "2026-04-10"
  },
  {
    "id": 2,
    "name": "Nusrat Jahan",
    "picture": "https://randomuser.me/api/portraits/women/44.jpg",
    "email": "nusrat.jahan@gmail.com",
    "days_since_contact": "10 day ago",
    "status": "almost due",
    "tags": ["school", "creative"],
    "bio": "School friend who is now a graphic designer. Loves sharing design ideas and trends.",
    "goal": 11,
    "next_due_date": "2026-04-20"
  },
  {
    "id": 3,
    "name": "Mahmudul Hasan",
    "picture": "https://randomuser.me/api/portraits/men/65.jpg",
    "email": "mahmudul.hasan@gmail.com",
    "days_since_contact": "5 day ago",
    "status": "on-track",
    "tags": ["office", "tech"],
    "bio": "Colleague at my first job. We still talk about web development and career growth.",
    "goal": 6,
    "next_due_date": "2026-04-25"
  },
  {
    "id": 4,
    "name": "Farhana Rahman",
    "picture": "https://randomuser.me/api/portraits/women/68.jpg",
    "email": "farhana.rahman@gmail.com",
    "days_since_contact": "21 day ago",
    "status": "overdue",
    "tags": ["family friend", "mentor"],
    "bio": "Older family friend who gives career advice and life guidance.",
    "goal": 18,
    "next_due_date": "2026-04-08"
  },
  {
    "id": 5,
    "name": "Tanvir Ahmed",
    "picture": "https://randomuser.me/api/portraits/men/21.jpg",
    "email": "tanvir.ahmed@gmail.com",
    "days_since_contact": "12 day ago",
    "status": "almost due",
    "tags": ["gym", "health"],
    "bio": "Workout partner who keeps me motivated. We share fitness routines and diet plans.",
    "goal": 19,
    "next_due_date": "2026-04-18"
  },
  {
    "id": 6,
    "name": "Sadia Islam",
    "picture": "https://randomuser.me/api/portraits/women/25.jpg",
    "email": "sadia.islam@gmail.com",
    "days_since_contact": "3 day ago",
    "status": "on-track",
    "tags": ["freelance", "network"],
    "bio": "Met through freelancing projects. We exchange client leads and productivity tips.",
    "goal": 15,
    "next_due_date": "2026-04-27"
  },
  {
    "id": 7,
    "name": "Rafiul Karim",
    "picture": "https://randomuser.me/api/portraits/men/78.jpg",
    "email": "rafiul.karim@gmail.com",
    "days_since_contact": "16 day ago",
    "status": "overdue",
    "tags": ["childhood", "travel"],
    "bio": "Childhood friend. We used to travel during holidays and still plan trips occasionally.",
    "goal": 1,
    "next_due_date": "2026-04-12"
  },
  {
    "id": 8,
    "name": "Mehjabin Chowdhury",
    "picture": "https://randomuser.me/api/portraits/women/12.jpg",
    "email": "mehjabin.c@gmail.com",
    "days_since_contact": "7 day ago",
    "status": "on-track",
    "tags": ["book club", "intellectual"],
    "bio": "We meet monthly for book discussions. She always recommends insightful reads.",
    "goal": 13,
    "next_due_date": "2026-04-23"
  }
]